rocs_client/__init__.py
rocs_client/common/__init__.py
rocs_client/common/camera.py
rocs_client/common/system.py
rocs_client/end_effector/__init__.py
rocs_client/end_effector/end_effector.py
rocs_client/motor/__init__.py
rocs_client/motor/motor.py
rocs_client/robot/__init__.py
rocs_client/robot/car.py
rocs_client/robot/human.py
rocs_client/robot/robot_base.py
rocs_client-1.3.11.dist-info/LICENSE
rocs_client-1.3.11.dist-info/METADATA
rocs_client-1.3.11.dist-info/WHEEL
rocs_client-1.3.11.dist-info/top_level.txt
rocs_client-1.3.11.dist-info/RECORD
